ztchooks/__init__.py
ztchooks/hook.py
ztchooks-0.1.1.dist-info/METADATA
ztchooks-0.1.1.dist-info/WHEEL
ztchooks-0.1.1.dist-info/licenses/LICENSE
ztchooks-0.1.1.dist-info/RECORD
