Metadata-Version: 2.1
Name: ztchooks
Version: 0.1.1
Summary: ZeroTier Hook Verification for Python 3
Project-URL: Homepage, https://github.com/zerotier/ztchooks-py
Project-URL: Bug Tracker, https://github.com/zerotier/ztchooks-py/issues
Author-email: "ZeroTier, Inc" <admin@zerotier.com>
License: 
License-File: LICENSE
Classifier: License :: OSI Approved :: Mozilla Public License 2.0 (MPL 2.0)
Classifier: Operating System :: OS Independent
Classifier: Programming Language :: Python :: 3
Requires-Python: >=3.9
